dist/README.md
dist/main.py
dist/tester.py
attendance_manager-0.1.0.dist-info/LICENSE
attendance_manager-0.1.0.dist-info/METADATA
attendance_manager-0.1.0.dist-info/WHEEL
attendance_manager-0.1.0.dist-info/top_level.txt
attendance_manager-0.1.0.dist-info/RECORD
