Metadata-Version: 2.1
Name: attendance-manager
Version: 0.1.0
Summary: A Python application for managing attendance and student data.
Author-email: Your Name <your.email@example.com>
License: /*
License-File: LICENSE
